{
  "id": "hupu-hot.1771389756645",
  "lastUpdatedAt": "2026-02-18 12:42:36",
  "data": [
    {
      "title": "[流言板]Shams: 梅森-普拉姆利与马刺签下一份10天短合同",
      "url": "https://bbs.hupu.com/637538896.html",
      "createdAt": "2026-02-18 12:42:13",
      "hot": 1
    },
    {
      "title": "[流言板]字母哥：首要目标是在雄鹿夺冠，否则可能重新考虑去向",
      "url": "https://bbs.hupu.com/637538402.html",
      "createdAt": "2026-02-18 12:42:13",
      "hot": 2
    },
    {
      "title": "[流言板]美记：东契奇对湖人截止日前的低调运作没有任何意见",
      "url": "https://bbs.hupu.com/637538629.html",
      "createdAt": "2026-02-18 12:42:13",
      "hot": 3
    },
    {
      "title": "[流言板]艾顿因携带大麻于巴哈马机场被扣留，律师澄清已获释",
      "url": "https://bbs.hupu.com/637539978.html",
      "createdAt": "2026-02-18 12:42:13",
      "hot": 4
    },
    {
      "title": "[流言板]保罗：在被送回家前的一周，弗兰克还说我是出色的领袖",
      "url": "https://bbs.hupu.com/637538576.html",
      "createdAt": "2026-02-18 12:42:13",
      "hot": 5
    },
    {
      "title": "[流言板]美记：塔图姆仍未就是否在本赛季出战做出决定",
      "url": "https://bbs.hupu.com/637538904.html",
      "createdAt": "2026-02-18 12:42:13",
      "hot": 6
    },
    {
      "title": "[流言板]布伦森谈续约：我希望他们公平对待我，我做出了牺牲",
      "url": "https://bbs.hupu.com/637538657.html",
      "createdAt": "2026-02-18 12:42:13",
      "hot": 7
    },
    {
      "title": "[流言板]爵士官方：小贾伦-杰克逊接受左膝PVNS手术，四周后评估",
      "url": "https://bbs.hupu.com/637538665.html",
      "createdAt": "2026-02-18 12:42:13",
      "hot": 8
    },
    {
      "title": "[流言板]鲍尔：我并不觉得自己打得那么差，我成了替罪羊",
      "url": "https://bbs.hupu.com/637538541.html",
      "createdAt": "2026-02-18 12:42:13",
      "hot": 9
    },
    {
      "title": "[流言板]丹尼-格林：我不确定东契奇和阿德托昆博的组合是否行得通",
      "url": "https://bbs.hupu.com/637538606.html",
      "createdAt": "2026-02-18 12:42:13",
      "hot": 10
    },
    {
      "title": "加拉塔萨雷5-2尤文，库普梅纳斯双响，卡巴尔替补染红",
      "url": "https://bbs.hupu.com/637537943.html",
      "createdAt": "2026-02-18 12:42:13",
      "hot": 1
    },
    {
      "title": "[流言板]欧足联将展开对普雷斯蒂安尼的调查，若属实将禁赛至少十场",
      "url": "https://bbs.hupu.com/637538872.html",
      "createdAt": "2026-02-18 12:42:13",
      "hot": 2
    },
    {
      "title": "[流言板]穆帅：裁判手里有张纸条，写着三名皇马球员再吃黄牌就停赛",
      "url": "https://bbs.hupu.com/637538384.html",
      "createdAt": "2026-02-18 12:42:13",
      "hot": 3
    },
    {
      "title": "欧冠：本菲卡0-1皇马，维尼破门，双方冲突比赛一度中断",
      "url": "https://bbs.hupu.com/637538260.html",
      "createdAt": "2026-02-18 12:42:13",
      "hot": 4
    },
    {
      "title": "[流言板]普雷斯安蒂尼：我想澄清从未种族歧视维尼修斯，遗憾他听错",
      "url": "https://bbs.hupu.com/637539100.html",
      "createdAt": "2026-02-18 12:42:13",
      "hot": 5
    },
    {
      "title": "[流言板]与维尼修斯冲突后，普雷斯蒂安尼社媒评论区已被关闭",
      "url": "https://bbs.hupu.com/637538222.html",
      "createdAt": "2026-02-18 12:42:13",
      "hot": 6
    },
    {
      "title": "[流言板]维尼修斯：种族主义者是懦夫，他们说话还要把嘴给捂上",
      "url": "https://bbs.hupu.com/637538451.html",
      "createdAt": "2026-02-18 12:42:13",
      "hot": 7
    },
    {
      "title": "[流言板]穆帅：我不想说维尼是骗子，也不想说普雷斯蒂安尼是好孩子",
      "url": "https://bbs.hupu.com/637538444.html",
      "createdAt": "2026-02-18 12:42:13",
      "hot": 8
    },
    {
      "title": "[流言板]穆里尼奥第二次在欧冠染红，上次是2011年欧冠半决赛",
      "url": "https://bbs.hupu.com/637538251.html",
      "createdAt": "2026-02-18 12:42:13",
      "hot": 9
    },
    {
      "title": "[流言板]斯内德：奥塔门迪脑子有问题，他的奖杯只是靠抱梅西大腿",
      "url": "https://bbs.hupu.com/637538691.html",
      "createdAt": "2026-02-18 12:42:13",
      "hot": 10
    },
    {
      "title": "我的炒股经历，希望大家引以为戒。目前绝望之谷，希望大家建言献策。",
      "url": "https://bbs.hupu.com/637538758.html",
      "createdAt": "2026-02-18 12:42:13",
      "hot": 1
    },
    {
      "title": "感觉亲戚之间很多都是假客套呢，一年见不了几次，见面比亲人还亲",
      "url": "https://bbs.hupu.com/637538880.html",
      "createdAt": "2026-02-18 12:42:13",
      "hot": 2
    },
    {
      "title": "现在知道为什么很多人支持禁止燃放鞭炮了",
      "url": "https://bbs.hupu.com/637538615.html",
      "createdAt": "2026-02-18 12:42:13",
      "hot": 3
    },
    {
      "title": "八年长跑，准备结束",
      "url": "https://bbs.hupu.com/637538859.html",
      "createdAt": "2026-02-18 12:42:13",
      "hot": 4
    },
    {
      "title": "为什么清粉对满清这个称呼怎么这么敏感",
      "url": "https://bbs.hupu.com/637538801.html",
      "createdAt": "2026-02-18 12:42:13",
      "hot": 5
    },
    {
      "title": "新年好呀",
      "url": "https://bbs.hupu.com/637539238.html",
      "createdAt": "2026-02-18 12:42:13",
      "hot": 6
    },
    {
      "title": "参加个老婆奶奶的寿宴亏了我8000块钱",
      "url": "https://bbs.hupu.com/637539492.html",
      "createdAt": "2026-02-18 12:42:13",
      "hot": 7
    },
    {
      "title": "大年初一因为钱的事和媳妇吵了一架，有没有老哥给开导下的",
      "url": "https://bbs.hupu.com/637539048.html",
      "createdAt": "2026-02-18 12:42:13",
      "hot": 8
    },
    {
      "title": "二婚家庭那些事，求开导！",
      "url": "https://bbs.hupu.com/637539263.html",
      "createdAt": "2026-02-18 12:42:13",
      "hot": 9
    },
    {
      "title": "宋祖英状态也太好了",
      "url": "https://bbs.hupu.com/637538570.html",
      "createdAt": "2026-02-18 12:42:13",
      "hot": 10
    }
  ]
}